{
  "homepage": "https://github.com/t1m0thyj/WinDynamicDesktop",
  "description": "Port of macOS Mojave Dynamic Desktop feature to Windows 10",
  "version": "4.7.0",
  "license": "MPL-2.0",
  "url": "https://github.com/t1m0thyj/WinDynamicDesktop/releases/download/v4.7.0/WinDynamicDesktop_Portable.exe",
  "hash": "b464ac8ef09224af70f759510e0971029eca56aaa3a70d527e67093e614ff245",
  "bin": "WinDynamicDesktop_Portable.exe",
  "shortcuts": [
      [
          "WinDynamicDesktop_Portable.exe",
          "WinDynamicDesktop"
      ]
  ]
}